GenerIter/__init__.py
GenerIter/config.py
GenerIter/excepts.py
GenerIter/factory.py
GenerIter/process.py
GenerIter/selector.py
GenerIter/source.py
GenerIter/util.py
GenerIter/app/__init__.py
GenerIter/app/algorithm.py
GenerIter/app/categorise.py
GenerIter/app/clep_algorithm.py
GenerIter/app/clep_categorise.py
GenerIter/app/clep_generator.py
GenerIter/app/clep_inventory.py
GenerIter/app/clibase.py
GenerIter/app/generator.py
GenerIter/app/inventory.py
GenerIter/processor/Basic.py
GenerIter/processor/Beats.py
GenerIter/processor/Mix.py
GenerIter/processor/Solo.py
GenerIter/processor/__init__.py
GenerIter-0.2.2.dist-info/LICENSE
GenerIter-0.2.2.dist-info/METADATA
GenerIter-0.2.2.dist-info/WHEEL
GenerIter-0.2.2.dist-info/entry_points.txt
GenerIter-0.2.2.dist-info/top_level.txt
GenerIter-0.2.2.dist-info/RECORD
