Metadata-Version: 2.1
Name: GenerIter
Version: 0.2.2
Summary: A package for Generative Iterative music composition.
Home-page: https://github.com/GridPresence/GenerIter
Author: Thomas Jackson Park & Jeremy Pavier
Author-email: generiter@gmx.com
License: MIT
Platform: UNKNOWN
Classifier: Programming Language :: Python :: 3
Classifier: License :: OSI Approved :: MIT License
Classifier: Operating System :: OS Independent
Requires-Python: >=3.6
Requires-Dist: pydub
